MANIFEST.in
README.rst
setup.py
docs/HISTORY.txt
docs/LICENSE.GPL
docs/LICENSE.txt
docs/inflate.png
ftw/__init__.py
ftw.inflator.egg-info/PKG-INFO
ftw.inflator.egg-info/SOURCES.txt
ftw.inflator.egg-info/dependency_links.txt
ftw.inflator.egg-info/entry_points.txt
ftw.inflator.egg-info/namespace_packages.txt
ftw.inflator.egg-info/not-zip-safe
ftw.inflator.egg-info/requires.txt
ftw.inflator.egg-info/top_level.txt
ftw/inflator/__init__.py
ftw/inflator/bundle.py
ftw/inflator/configure.zcml
ftw/inflator/customization.py
ftw/inflator/exceptions.py
ftw/inflator/hooks.py
ftw/inflator/interfaces.py
ftw/inflator/meta.py
ftw/inflator/meta.zcml
ftw/inflator/overrides.zcml
ftw/inflator/testing.py
ftw/inflator/browser/__init__.py
ftw/inflator/browser/configure.zcml
ftw/inflator/browser/inflate.pt
ftw/inflator/browser/overview.pt
ftw/inflator/browser/overview_plone5.pt
ftw/inflator/browser/views.py
ftw/inflator/creation/__init__.py
ftw/inflator/creation/configure.zcml
ftw/inflator/creation/content_creation.cfg
ftw/inflator/creation/progresslogger.py
ftw/inflator/creation/setuphandler.py
ftw/inflator/creation/single_item_content_creation.cfg
ftw/inflator/creation/sections/__init__.py
ftw/inflator/creation/sections/annotations.py
ftw/inflator/creation/sections/base.py
ftw/inflator/creation/sections/constraintypes.py
ftw/inflator/creation/sections/files.py
ftw/inflator/creation/sections/helpers.py
ftw/inflator/creation/sections/interfaces.py
ftw/inflator/creation/sections/jsonsource.py
ftw/inflator/creation/sections/local_roles.py
ftw/inflator/creation/sections/multilingual.py
ftw/inflator/creation/sections/placefulworkflow.py
ftw/inflator/creation/sections/portlets.py
ftw/inflator/creation/sections/properties.py
ftw/inflator/creation/sections/resolvepath.py
ftw/inflator/creation/sections/resolvetree.py
ftw/inflator/creation/sections/resolveuuid.py
ftw/inflator/creation/sections/schemaupdater.py
ftw/inflator/creation/sections/singleitemsource.py
ftw/inflator/creation/sections/translate.py
ftw/inflator/creation/sections/utils.py
ftw/inflator/locales/ftw.inflator.pot
ftw/inflator/locales/de/LC_MESSAGES/ftw.inflator.po
ftw/inflator/patches/__init__.py
ftw/inflator/patches/configure.zcml
ftw/inflator/profiles/setup-language/.keep
ftw/inflator/resources/plone-logo.png
