Metadata-Version: 2.1
Name: ftw.inflator
Version: 1.11.0
Summary: Plone site setup wizard with content creation and bundle system for predefined configurations.
Home-page: https://github.com/4teamwork/ftw.inflator
Author: 4teamwork AG
Author-email: mailto:info@4teamwork.ch
License: GPL2
Keywords: ftw inflator
Platform: UNKNOWN
Classifier: Framework :: Plone
Classifier: Framework :: Plone :: 4.3
Classifier: Framework :: Plone :: 5.1
Classifier: Intended Audience :: Developers
Classifier: Topic :: Software Development :: Libraries :: Python Modules
Provides-Extra: dexterity
Provides-Extra: tests
Provides-Extra: multilingual
Provides-Extra: plone4_multilingual
